{
    "Table": {
        "User": {
            "userId": { "type": "String" },
            "userName": { "type": "String" },
            "bio": { "type": "String" },
            "avatar": { "type": "String" },
            "password": { "type": "String" },
            "createAt": {"type": "TimeStamp"}
        },
        "Song":{
            "songId": { "type": "Int" },
            "listId": { "type": "Int" },
            "url": { "type": "String" },
            "songName": { "type": "String" },
            "songCover": { "type": "String" },
            "songDes": { "type": "String" },
            "createAt": { "type": "TimeStamp" },
            "updateAt": { "type": "TimeStamp" }
        },
        "List":{
            "listId": { "type": "Int" },
            "userId": { "type": "String" },
            "listName" : { "type": "String" },
            "listDes" : { "type": "String" },
            "listCover": { "type": "String"},
            "createAt": { "type": "TimeStamp" },
            "updateAt": { "type": "TimeStamp" }
        }
    }
}
